{
    "Request": "Modify_event",
    "User": {   
        "email": "user1@gmail.com",      
        "pw_hash": "XXA83jd3kljsdf",    
        "ip": "143.248.143.29"  
    },    
    "Event": {
        "abstract": "Superman is the best (optional)",
        "place": "Kaist (optional",
        "time": "2018-11-03 03:01:00.914138+00:00 (optional",         
        "title": "Superman (optional",         
        "details": "Blabla (optional",
        "poster_image": "imageimage (optional",
        "speaker": "Harlem (optional"
    }
}